{
	"!Type": "AssetCreature",
	"AssetID": "09a922d6-c348-490a-960b-9095199ae5e9",
	"AssetName": "CR_TrainingDummy2",
	"ObjectName": "Prey",
	"ObjectAlias": "the prey",
	"Strength": 3,
	"Agility": 3,
	"Body": 4,
	"Wits": 3,
	"Flags": 30,
	"Level": 1,
	"Size": "Medium",
	"Gender": "Ungendered",
	"Equipment1": null,
	"Equipment2": null,
	"Equipment3": null,
	"Equipment4": null,
	"IsPredator": false,
	"AutoVorePrey": false,
	"StringMappings": [
		{
			"Key": "GRAPPLE_HIT",
			"Rule": "Always",
			"NewKey": "TDUMMY_GRAPPLE_HIT"
		},
		{
			"Key": "GRAPPLE_MISS",
			"Rule": "Always",
			"NewKey": "TDUMMY_GRAPPLE_MISS"
		}
	]
}