{
	"!Type": "AssetCreature",
	"ID": "09a922d6-c348-490a-960b-9095199ae5e9",
	"Name": "CR_TrainingDummy2",
	"ObjectName": "Prey",
	"ObjectAlias": "the prey",
	"Strength": 0,
	"Agility": 0,
	"Body": 2,
	"Wits": 0,
	"Flags": 252,
	"Level": 1,
	"Size": "Medium",
	"Gender": "Neuter",
	"Equipment1": "00000000-0000-0000-0000-000000000000",
	"Equipment2": "00000000-0000-0000-0000-000000000000",
	"Equipment3": "00000000-0000-0000-0000-000000000000",
	"Equipment4": "00000000-0000-0000-0000-000000000000",
	"IsPredator": false,
	"AutoVorePrey": false,
	"StringMappings": [
		{
			"Key": "GRAPPLE_HIT",
			"Rule": "Always",
			"NewKey": "TDUMMY_GRAPPLE_HIT"
		},
		{
			"Key": "GRAPPLE_MISS",
			"Rule": "Always",
			"NewKey": "TDUMMY_GRAPPLE_MISS"
		}
	]
}