{
	"!Type": "AssetScene",
	"AssetID": "8d5f166c-a747-4d83-9cbc-069187723512",
	"AssetName": "Scene_PortTemple",
	"ScriptEnter": {
		"!Type": "ScriptDataVisualAction",
		"Nodes": [
			{
				"!Type": "CommandSetLocation",
				"OperandMode": "Literal",
				"OperandText": "South Finmer, Shrine"
			},
			{
				"!Type": "CommandSetInventoryEnabled",
				"OperandMode": "Literal",
				"OperandLiteral": true
			}
		]
	},
	"IsPatch": false,
	"Root": {
		"NodeType": "Root",
		"Key": "Root",
		"Children": [
			{
				"NodeType": "State",
				"Key": "Empty",
				"ScriptAction": {
					"!Type": "ScriptDataVisualAction",
					"Nodes": [
						{
							"!Type": "CommandLog",
							"Text": "PORT_TEMPLE_POSTMQ03_EMPTY",
							"IsRaw": false
						}
					]
				},
				"ScriptAppear": {
					"!Type": "ScriptDataVisualCondition",
					"Mode": "All",
					"Operand": true,
					"Tests": [
						{
							"!Type": "ConditionVarFlag",
							"VariableName": "MQ03_DONE",
							"OperandMode": "Literal",
							"OperandLiteral": true
						},
						{
							"!Type": "ConditionVarFlag",
							"VariableName": "PORT_TEMPLE_REOPENED",
							"OperandMode": "Literal",
							"OperandLiteral": false
						}
					]
				},
				"Children": [
					{
						"NodeType": "Choice",
						"Key": "Empty_C_Leave",
						"Title": "Leave",
						"Tooltip": "There's not much else to do here.",
						"Highlight": false,
						"ButtonWidth": 1.0,
						"ScriptAction": {
							"!Type": "ScriptDataVisualAction",
							"Nodes": [
								{
									"!Type": "CommandSetScene",
									"SceneGuid": "e6b01216-c0e8-4438-9da3-8f3587458706"
								}
							]
						},
						"Children": []
					},
					{
						"NodeType": "Choice",
						"Key": "Empty_C_Rest",
						"Title": "Rest",
						"Tooltip": "Rest for a moment and record your progress.",
						"Highlight": false,
						"ButtonWidth": 1.0,
						"Children": [
							{
								"NodeType": "State",
								"Key": "Empty_R_Rest",
								"ScriptAction": {
									"!Type": "ScriptDataVisualAction",
									"Nodes": [
										{
											"!Type": "CommandPlayerHealAll"
										},
										{
											"!Type": "CommandSaveDialog"
										},
										{
											"!Type": "CommandLog",
											"Text": "PORT_TEMPLE_REST",
											"IsRaw": false
										}
									]
								},
								"Children": [
									{
										"NodeType": "Link",
										"LinkTarget": "Empty_C_Leave"
									}
								]
							}
						]
					}
				]
			},
			{
				"NodeType": "State",
				"Key": "EnterFirst",
				"ScriptAction": {
					"!Type": "ScriptDataVisualAction",
					"Nodes": [
						{
							"!Type": "CommandLog",
							"Text": "PORT_TEMPLE_ENTER_FIRST",
							"IsRaw": false
						},
						{
							"!Type": "CommandVarSetFlag",
							"VariableName": "PORT_TEMPLE_ENTER_FIRST",
							"OperandMode": "Literal",
							"OperandLiteral": true
						}
					]
				},
				"ScriptAppear": {
					"!Type": "ScriptDataVisualCondition",
					"Mode": "All",
					"Operand": true,
					"Tests": [
						{
							"!Type": "ConditionVarFlag",
							"VariableName": "PORT_TEMPLE_ENTER_FIRST",
							"OperandMode": "Literal",
							"OperandLiteral": false
						}
					]
				},
				"Children": [
					{
						"NodeType": "Choice",
						"Key": "EnterFirst_C_Intro2",
						"Title": "Continue",
						"Highlight": false,
						"ButtonWidth": 1.0,
						"Children": [
							{
								"NodeType": "State",
								"Key": "EnterFirst_R_Intro2",
								"ScriptAction": {
									"!Type": "ScriptDataVisualAction",
									"Nodes": [
										{
											"!Type": "CommandLog",
											"Text": "PORT_TEMPLE_ENTER_FIRST2",
											"IsRaw": false
										}
									]
								},
								"Children": [
									{
										"NodeType": "Choice",
										"Key": "EnterFirst_C_Who",
										"Title": "Greet",
										"Tooltip": "Exchange pleasantries.",
										"Highlight": false,
										"ButtonWidth": 1.0,
										"Children": [
											{
												"NodeType": "State",
												"Key": "EnterFirst_R_Who",
												"ScriptAction": {
													"!Type": "ScriptDataVisualAction",
													"Nodes": [
														{
															"!Type": "CommandLog",
															"Text": "PORT_TEMPLE_TALK_WHO",
															"IsRaw": false
														}
													]
												},
												"Children": [
													{
														"NodeType": "Link",
														"LinkTarget": "Talk_C_Iso"
													},
													{
														"NodeType": "Link",
														"LinkTarget": "Talk_C_Spirits"
													},
													{
														"NodeType": "Link",
														"LinkTarget": "Talk_C_Shore"
													},
													{
														"NodeType": "Link",
														"LinkTarget": "Talk_C_Amber"
													},
													{
														"NodeType": "Link",
														"LinkTarget": "Talk_C_Adept"
													}
												]
											}
										]
									}
								]
							}
						]
					}
				]
			},
			{
				"NodeType": "State",
				"Key": "Main",
				"ScriptAction": {
					"!Type": "ScriptDataVisualAction",
					"Nodes": [
						{
							"!Type": "CommandLog",
							"Text": "PORT_TEMPLE_ENTER",
							"IsRaw": false
						}
					]
				},
				"Children": [
					{
						"NodeType": "Choice",
						"Key": "Main_C_FakeLeaveMQ03",
						"Title": "Leave",
						"Tooltip": "Return outside...",
						"Highlight": false,
						"ButtonWidth": 1.0,
						"ScriptAppear": {
							"!Type": "ScriptDataVisualCondition",
							"Mode": "All",
							"Operand": true,
							"Tests": [
								{
									"!Type": "ConditionVarFlag",
									"VariableName": "MQ03_TEMPLE_EVENT",
									"OperandMode": "Literal",
									"OperandLiteral": false
								},
								{
									"!Type": "ConditionVarFlag",
									"VariableName": "MQ03_TAVERN_EVENT",
									"OperandMode": "Literal",
									"OperandLiteral": true
								},
								{
									"!Type": "ConditionInlineSnippet",
									"Snippet": "GetIsNight()"
								}
							]
						},
						"Children": [
							{
								"NodeType": "Link",
								"LinkTarget": "MQ03_Event_Intro"
							}
						]
					},
					{
						"NodeType": "Choice",
						"Key": "Main_C_Leave",
						"Title": "Leave",
						"Tooltip": "Return outside.",
						"Highlight": false,
						"ButtonWidth": 1.0,
						"ScriptAction": {
							"!Type": "ScriptDataVisualAction",
							"Nodes": [
								{
									"!Type": "CommandSetScene",
									"SceneGuid": "e6b01216-c0e8-4438-9da3-8f3587458706"
								}
							]
						},
						"ScriptAppear": {
							"!Type": "ScriptDataVisualCondition",
							"Mode": "Any",
							"Operand": false,
							"Tests": [
								{
									"!Type": "ConditionVarFlag",
									"VariableName": "MQ03_TEMPLE_EVENT",
									"OperandMode": "Literal",
									"OperandLiteral": false
								},
								{
									"!Type": "ConditionVarFlag",
									"VariableName": "MQ03_TAVERN_EVENT",
									"OperandMode": "Literal",
									"OperandLiteral": true
								},
								{
									"!Type": "ConditionInlineSnippet",
									"Snippet": "GetIsNight()"
								}
							]
						},
						"Children": []
					},
					{
						"NodeType": "Choice",
						"Key": "Main_C_Talk",
						"Title": "Talk",
						"Tooltip": "Speak with the priestess.",
						"Highlight": false,
						"ButtonWidth": 1.0,
						"Children": [
							{
								"NodeType": "State",
								"Key": "Talk_Root",
								"Children": [
									{
										"NodeType": "Choice",
										"Key": "Talk_C_Back",
										"Title": "(Back)",
										"Highlight": false,
										"ButtonWidth": 0.75,
										"Children": [
											{
												"NodeType": "State",
												"Children": [
													{
														"NodeType": "Link",
														"LinkTarget": "Main_C_FakeLeaveMQ03"
													},
													{
														"NodeType": "Link",
														"LinkTarget": "Main_C_Leave"
													},
													{
														"NodeType": "Link",
														"LinkTarget": "Main_C_Talk"
													},
													{
														"NodeType": "Link",
														"LinkTarget": "Main_C_Rest"
													}
												]
											}
										]
									},
									{
										"NodeType": "Choice",
										"Key": "Talk_C_Iso",
										"Title": "Iso",
										"Tooltip": "Ask Willow if she has seen Iso around.",
										"Highlight": false,
										"ButtonWidth": 1.0,
										"ScriptAppear": {
											"!Type": "ScriptDataVisualCondition",
											"Mode": "All",
											"Operand": true,
											"Tests": [
												{
													"!Type": "ConditionVarFlag",
													"VariableName": "PORT_TEMPLE_TALK_ISO",
													"OperandMode": "Literal",
													"OperandLiteral": false
												},
												{
													"!Type": "ConditionVarFlag",
													"VariableName": "MQ03_TEMPLE_EVENT",
													"OperandMode": "Literal",
													"OperandLiteral": false
												}
											]
										},
										"Children": [
											{
												"NodeType": "State",
												"Key": "Talk_R_Iso",
												"ScriptAction": {
													"!Type": "ScriptDataVisualAction",
													"Nodes": [
														{
															"!Type": "CommandLog",
															"Text": "PORT_TEMPLE_TALK_ISO",
															"IsRaw": false
														},
														{
															"!Type": "CommandVarSetFlag",
															"VariableName": "PORT_TEMPLE_TALK_ISO",
															"OperandMode": "Literal",
															"OperandLiteral": true
														},
														{
															"!Type": "CommandInlineSnippet",
															"Snippet": "MQ03_IncrementGossip()"
														}
													]
												},
												"Children": [
													{
														"NodeType": "Link",
														"LinkTarget": "Talk_C_Back"
													},
													{
														"NodeType": "Link",
														"LinkTarget": "Talk_C_Spirits"
													},
													{
														"NodeType": "Link",
														"LinkTarget": "Talk_C_Shore"
													},
													{
														"NodeType": "Link",
														"LinkTarget": "Talk_C_Amber"
													},
													{
														"NodeType": "Link",
														"LinkTarget": "Talk_C_Adept"
													},
													{
														"NodeType": "Link",
														"LinkTarget": "Talk_C_Book"
													}
												]
											}
										]
									},
									{
										"NodeType": "Choice",
										"Key": "Talk_C_Spirits",
										"Title": "Spirits",
										"Tooltip": "Ask her to tell you more about these spirits she talked about.",
										"Highlight": false,
										"ButtonWidth": 1.0,
										"ScriptAppear": {
											"!Type": "ScriptDataVisualCondition",
											"Mode": "All",
											"Operand": true,
											"Tests": [
												{
													"!Type": "ConditionVarFlag",
													"VariableName": "PORT_TEMPLE_TALK_SPIRITS",
													"OperandMode": "Literal",
													"OperandLiteral": false
												}
											]
										},
										"Children": [
											{
												"NodeType": "State",
												"Key": "Talk_R_Spirits",
												"ScriptAction": {
													"!Type": "ScriptDataVisualAction",
													"Nodes": [
														{
															"!Type": "CommandLog",
															"Text": "PORT_TEMPLE_TALK_SPIRITS",
															"IsRaw": false
														},
														{
															"!Type": "CommandVarSetFlag",
															"VariableName": "PORT_TEMPLE_TALK_SPIRITS",
															"OperandMode": "Literal",
															"OperandLiteral": true
														}
													]
												},
												"Children": [
													{
														"NodeType": "Link",
														"LinkTarget": "Talk_C_Back"
													},
													{
														"NodeType": "Link",
														"LinkTarget": "Talk_C_Iso"
													},
													{
														"NodeType": "Link",
														"LinkTarget": "Talk_C_Shore"
													},
													{
														"NodeType": "Link",
														"LinkTarget": "Talk_C_Amber"
													},
													{
														"NodeType": "Link",
														"LinkTarget": "Talk_C_Adept"
													},
													{
														"NodeType": "Link",
														"LinkTarget": "Talk_C_Book"
													}
												]
											}
										]
									},
									{
										"NodeType": "Choice",
										"Key": "Talk_C_Shore",
										"Title": "The Shore",
										"Tooltip": "Ask what she knows of this mystical 'shore'.",
										"Highlight": false,
										"ButtonWidth": 1.0,
										"ScriptAppear": {
											"!Type": "ScriptDataVisualCondition",
											"Mode": "Any",
											"Operand": true,
											"Tests": [
												{
													"!Type": "ConditionVarFlag",
													"VariableName": "PORT_TEMPLE_TALK_SPIRITS",
													"OperandMode": "Literal",
													"OperandLiteral": true
												},
												{
													"!Type": "ConditionVarFlag",
													"VariableName": "ABBEY_EXPLORE_WORKSHOP_S1",
													"OperandMode": "Literal",
													"OperandLiteral": true
												},
												{
													"!Type": "ConditionVarFlag",
													"VariableName": "PORT_TEMPLE_TALK_SHORE",
													"OperandMode": "Literal",
													"OperandLiteral": false
												}
											]
										},
										"Children": [
											{
												"NodeType": "State",
												"Key": "Talk_R_Shore",
												"ScriptAction": {
													"!Type": "ScriptDataVisualAction",
													"Nodes": [
														{
															"!Type": "CommandLog",
															"Text": "PORT_TEMPLE_TALK_SHORE",
															"IsRaw": false
														},
														{
															"!Type": "CommandVarSetFlag",
															"VariableName": "PORT_TEMPLE_TALK_SHORE",
															"OperandMode": "Literal",
															"OperandLiteral": true
														}
													]
												},
												"Children": [
													{
														"NodeType": "Link",
														"LinkTarget": "Talk_C_Back"
													},
													{
														"NodeType": "Link",
														"LinkTarget": "Talk_C_Iso"
													},
													{
														"NodeType": "Link",
														"LinkTarget": "Talk_C_Spirits"
													},
													{
														"NodeType": "Link",
														"LinkTarget": "Talk_C_Amber"
													},
													{
														"NodeType": "Link",
														"LinkTarget": "Talk_C_Adept"
													},
													{
														"NodeType": "Link",
														"LinkTarget": "Talk_C_Book"
													}
												]
											}
										]
									},
									{
										"NodeType": "Choice",
										"Key": "Talk_C_Amber",
										"Title": "Amber",
										"Tooltip": "Ask about the amber crystals you've heard about.",
										"Highlight": false,
										"ButtonWidth": 1.0,
										"ScriptAppear": {
											"!Type": "ScriptDataVisualCondition",
											"Mode": "Any",
											"Operand": true,
											"Tests": [
												{
													"!Type": "ConditionVarFlag",
													"VariableName": "MQ03_TAVERN_EVENT_AMBER",
													"OperandMode": "Literal",
													"OperandLiteral": true
												},
												{
													"!Type": "ConditionVarFlag",
													"VariableName": "TOWN_ALCH_STOLEN",
													"OperandMode": "Literal",
													"OperandLiteral": true
												},
												{
													"!Type": "ConditionVarFlag",
													"VariableName": "OLIVER_DEAD",
													"OperandMode": "Literal",
													"OperandLiteral": true
												},
												{
													"!Type": "ConditionVarFlag",
													"VariableName": "PORT_TEMPLE_TALK_SHORE",
													"OperandMode": "Literal",
													"OperandLiteral": true
												}
											]
										},
										"Children": [
											{
												"NodeType": "State",
												"Key": "Talk_R_Amber",
												"ScriptAction": {
													"!Type": "ScriptDataVisualAction",
													"Nodes": [
														{
															"!Type": "CommandLog",
															"Text": "PORT_TEMPLE_TALK_AMBER",
															"IsRaw": false
														},
														{
															"!Type": "CommandVarSetFlag",
															"VariableName": "PORT_TEMPLE_TALK_AMBER",
															"OperandMode": "Literal",
															"OperandLiteral": true
														}
													]
												},
												"Children": [
													{
														"NodeType": "Choice",
														"Title": "Possession",
														"Tooltip": "Say that you found some on your journey.",
														"Highlight": false,
														"ButtonWidth": 1.0,
														"Children": [
															{
																"NodeType": "State",
																"Key": "Talk_R_Amber2",
																"ScriptAction": {
																	"!Type": "ScriptDataVisualAction",
																	"Nodes": [
																		{
																			"!Type": "CommandLog",
																			"Text": "PORT_TEMPLE_TALK_AMBER2",
																			"IsRaw": false
																		}
																	]
																},
																"Children": [
																	{
																		"NodeType": "Link",
																		"LinkTarget": "Talk_C_Back"
																	},
																	{
																		"NodeType": "Link",
																		"LinkTarget": "Talk_C_Iso"
																	},
																	{
																		"NodeType": "Link",
																		"LinkTarget": "Talk_C_Spirits"
																	},
																	{
																		"NodeType": "Link",
																		"LinkTarget": "Talk_C_Shore"
																	},
																	{
																		"NodeType": "Link",
																		"LinkTarget": "Talk_C_Adept"
																	},
																	{
																		"NodeType": "Link",
																		"LinkTarget": "Talk_C_Book"
																	}
																]
															}
														]
													},
													{
														"NodeType": "Choice",
														"Title": "Rumors",
														"Tooltip": "Say that you've overheard rumors about it.",
														"Highlight": false,
														"ButtonWidth": 1.0,
														"Children": [
															{
																"NodeType": "Link",
																"LinkTarget": "Talk_R_Amber2"
															}
														]
													},
													{
														"NodeType": "Choice",
														"Title": "Desire",
														"Tooltip": "Say that you seek to discover it for yourself.",
														"Highlight": false,
														"ButtonWidth": 1.0,
														"Children": [
															{
																"NodeType": "Link",
																"LinkTarget": "Talk_R_Amber2"
															}
														]
													}
												]
											}
										]
									},
									{
										"NodeType": "Choice",
										"Key": "Talk_C_Adept",
										"Title": "Adepts",
										"Tooltip": "Ask what Adepts are, then - are they trained users?",
										"Highlight": false,
										"ButtonWidth": 1.0,
										"ScriptAppear": {
											"!Type": "ScriptDataVisualCondition",
											"Mode": "Any",
											"Operand": true,
											"Tests": [
												{
													"!Type": "ConditionVarFlag",
													"VariableName": "PORT_TEMPLE_TALK_SHORE",
													"OperandMode": "Literal",
													"OperandLiteral": true
												},
												{
													"!Type": "ConditionVarFlag",
													"VariableName": "PORT_TEMPLE_TALK_AMBER",
													"OperandMode": "Literal",
													"OperandLiteral": true
												}
											]
										},
										"Children": [
											{
												"NodeType": "State",
												"Key": "Talk_R_Adept",
												"ScriptAction": {
													"!Type": "ScriptDataVisualAction",
													"Nodes": [
														{
															"!Type": "CommandLog",
															"Text": "PORT_TEMPLE_TALK_ADEPT",
															"IsRaw": false
														},
														{
															"!Type": "CommandVarSetFlag",
															"VariableName": "PORT_TEMPLE_TALK_ADEPT",
															"OperandMode": "Literal",
															"OperandLiteral": true
														}
													]
												},
												"Children": [
													{
														"NodeType": "Link",
														"LinkTarget": "Talk_C_Back"
													},
													{
														"NodeType": "Link",
														"LinkTarget": "Talk_C_Iso"
													},
													{
														"NodeType": "Link",
														"LinkTarget": "Talk_C_Spirits"
													},
													{
														"NodeType": "Link",
														"LinkTarget": "Talk_C_Shore"
													},
													{
														"NodeType": "Link",
														"LinkTarget": "Talk_C_Amber"
													},
													{
														"NodeType": "Link",
														"LinkTarget": "Talk_C_Book"
													}
												]
											}
										]
									},
									{
										"NodeType": "Choice",
										"Key": "Talk_C_Book",
										"Title": "Old Book",
										"Tooltip": "Show the old tome you found in Dalsida Abbey.",
										"Highlight": true,
										"ButtonWidth": 1.0,
										"ScriptAppear": {
											"!Type": "ScriptDataVisualCondition",
											"Mode": "All",
											"Operand": true,
											"Tests": [
												{
													"!Type": "ConditionPlayerHasItem",
													"ItemGuid": "b5225d74-e3fb-4561-bc60-d80be316335f"
												},
												{
													"!Type": "ConditionVarFlag",
													"VariableName": "PORT_TEMPLE_TALK_BOOK",
													"OperandMode": "Literal",
													"OperandLiteral": false
												}
											]
										},
										"Children": [
											{
												"NodeType": "State",
												"Key": "Talk_R_Book",
												"ScriptAction": {
													"!Type": "ScriptDataVisualAction",
													"Nodes": [
														{
															"!Type": "CommandLog",
															"Text": "PORT_TEMPLE_TALK_BOOK",
															"IsRaw": false
														},
														{
															"!Type": "CommandVarSetFlag",
															"VariableName": "PORT_TEMPLE_TALK_BOOK",
															"OperandMode": "Literal",
															"OperandLiteral": true
														}
													]
												},
												"Children": [
													{
														"NodeType": "Link",
														"LinkTarget": "Talk_C_Back"
													},
													{
														"NodeType": "Link",
														"LinkTarget": "Talk_C_Iso"
													},
													{
														"NodeType": "Link",
														"LinkTarget": "Talk_C_Spirits"
													},
													{
														"NodeType": "Link",
														"LinkTarget": "Talk_C_Shore"
													},
													{
														"NodeType": "Link",
														"LinkTarget": "Talk_C_Amber"
													},
													{
														"NodeType": "Link",
														"LinkTarget": "Talk_C_Adept"
													}
												]
											}
										]
									}
								]
							}
						]
					},
					{
						"NodeType": "Choice",
						"Key": "Main_C_Rest",
						"Title": "Rest",
						"Tooltip": "Rest for a moment and record your progress.",
						"Highlight": false,
						"ButtonWidth": 1.0,
						"Children": [
							{
								"NodeType": "State",
								"ScriptAction": {
									"!Type": "ScriptDataVisualAction",
									"Nodes": [
										{
											"!Type": "CommandPlayerHealAll"
										},
										{
											"!Type": "CommandSaveDialog"
										},
										{
											"!Type": "CommandLog",
											"Text": "PORT_TEMPLE_REST",
											"IsRaw": false
										}
									]
								},
								"Children": [
									{
										"NodeType": "Link",
										"LinkTarget": "Main_C_FakeLeaveMQ03"
									},
									{
										"NodeType": "Link",
										"LinkTarget": "Main_C_Leave"
									},
									{
										"NodeType": "Link",
										"LinkTarget": "Main_C_Talk"
									}
								]
							}
						]
					}
				]
			},
			{
				"NodeType": "State",
				"Key": "MQ03_Event_Intro",
				"ScriptAction": {
					"!Type": "ScriptDataVisualAction",
					"Nodes": [
						{
							"!Type": "CommandVarSetFlag",
							"VariableName": "MQ03_TEMPLE_EVENT",
							"OperandMode": "Literal",
							"OperandLiteral": true
						},
						{
							"!Type": "CommandSetInventoryEnabled",
							"OperandMode": "Literal",
							"OperandLiteral": false
						},
						{
							"!Type": "CommandLogSplit"
						},
						{
							"!Type": "CommandLog",
							"Text": "MQ03_TEMPLE_INTRO1",
							"IsRaw": false
						},
						{
							"!Type": "CommandComment",
							"Comment": "Replace Iso's ring with the \"revealed\" one"
						},
						{
							"!Type": "CommandIf",
							"Mode": "All",
							"Operand": true,
							"Tests": [
								{
									"!Type": "ConditionInlineSnippet",
									"Snippet": "Player.EquippedAccessory1 ~= nil and Player.EquippedAccessory1.AssetName == \"AC_IsoRing\""
								}
							],
							"HasElseBranch": true,
							"MainSubgroup": [
								{
									"!Type": "CommandPlayerSetEquipment",
									"EquipSlot": "Accessory1",
									"ItemGuid": "c2238bbd-9af9-4167-9024-2e631fec5f83"
								},
								{
									"!Type": "CommandVarSetFlag",
									"VariableName": "MQ03_TEMPLE_RING_WORN",
									"OperandMode": "Literal",
									"OperandLiteral": true
								}
							],
							"ElseSubgroup": [
								{
									"!Type": "CommandIf",
									"Mode": "All",
									"Operand": true,
									"Tests": [
										{
											"!Type": "ConditionInlineSnippet",
											"Snippet": "Player.EquippedAccessory2 ~= nil and Player.EquippedAccessory2.AssetName == \"AC_IsoRing\""
										}
									],
									"HasElseBranch": true,
									"MainSubgroup": [
										{
											"!Type": "CommandPlayerSetEquipment",
											"EquipSlot": "Accessory2",
											"ItemGuid": "c2238bbd-9af9-4167-9024-2e631fec5f83"
										},
										{
											"!Type": "CommandVarSetFlag",
											"VariableName": "MQ03_TEMPLE_RING_WORN",
											"OperandMode": "Literal",
											"OperandLiteral": true
										}
									],
									"ElseSubgroup": [
										{
											"!Type": "CommandPlayerSetItem",
											"ItemGuid": "9424541d-3712-4dc7-8c30-5934d1581317",
											"Add": false
										},
										{
											"!Type": "CommandPlayerSetItem",
											"ItemGuid": "c2238bbd-9af9-4167-9024-2e631fec5f83",
											"Add": true,
											"Quiet": true
										}
									]
								}
							]
						}
					]
				},
				"Children": [
					{
						"NodeType": "Choice",
						"Key": "MQ03_C_Intro2",
						"Title": "Continue",
						"Highlight": false,
						"ButtonWidth": 1.0,
						"Children": [
							{
								"NodeType": "State",
								"Key": "MQ03_R_Intro2",
								"ScriptAction": {
									"!Type": "ScriptDataVisualAction",
									"Nodes": [
										{
											"!Type": "CommandLog",
											"Text": "MQ03_TEMPLE_INTRO2",
											"IsRaw": false
										}
									]
								},
								"Children": [
									{
										"NodeType": "Choice",
										"Key": "MQ03_C_Intro3",
										"Title": "Explain",
										"Tooltip": "Something went wrong...",
										"Highlight": false,
										"ButtonWidth": 1.0,
										"Children": [
											{
												"NodeType": "State",
												"Key": "MQ03_R_Intro3",
												"ScriptAction": {
													"!Type": "ScriptDataVisualAction",
													"Nodes": [
														{
															"!Type": "CommandLog",
															"Text": "MQ03_TEMPLE_INTRO3",
															"IsRaw": false
														}
													]
												},
												"Children": [
													{
														"NodeType": "Choice",
														"Key": "MQ03_C_Intro4",
														"Title": "Continue",
														"Highlight": false,
														"ButtonWidth": 1.0,
														"Children": [
															{
																"NodeType": "State",
																"Key": "MQ03_R_Intro4Worn",
																"ScriptAction": {
																	"!Type": "ScriptDataVisualAction",
																	"Nodes": [
																		{
																			"!Type": "CommandLog",
																			"Text": "MQ03_TEMPLE_INTRO4_WORN",
																			"IsRaw": false
																		}
																	]
																},
																"ScriptAppear": {
																	"!Type": "ScriptDataVisualCondition",
																	"Mode": "All",
																	"Operand": true,
																	"Tests": [
																		{
																			"!Type": "ConditionVarFlag",
																			"VariableName": "MQ03_TEMPLE_RING_WORN",
																			"OperandMode": "Literal",
																			"OperandLiteral": true
																		}
																	]
																},
																"Children": [
																	{
																		"NodeType": "Choice",
																		"Title": "What",
																		"Tooltip": "Ask her if she knows what this ring is.",
																		"Highlight": false,
																		"ButtonWidth": 1.0,
																		"Children": [
																			{
																				"NodeType": "State",
																				"Key": "MQ03_R_Intro5",
																				"ScriptAction": {
																					"!Type": "ScriptDataVisualAction",
																					"Nodes": [
																						{
																							"!Type": "CommandLog",
																							"Text": "MQ03_TEMPLE_INTRO5",
																							"IsRaw": false
																						}
																					]
																				},
																				"Children": [
																					{
																						"NodeType": "Choice",
																						"Key": "MQ03_C_Intro6",
																						"Title": "Continue",
																						"Highlight": false,
																						"ButtonWidth": 1.0,
																						"Children": [
																							{
																								"NodeType": "State",
																								"Key": "MQ03_R_Intro6",
																								"ScriptAction": {
																									"!Type": "ScriptDataVisualAction",
																									"Nodes": [
																										{
																											"!Type": "CommandLog",
																											"Text": "MQ03_TEMPLE_INTRO6",
																											"IsRaw": false
																										}
																									]
																								},
																								"Children": [
																									{
																										"NodeType": "Choice",
																										"Title": "Rux",
																										"Tooltip": "Ask how she knows an Adept.",
																										"Highlight": false,
																										"ButtonWidth": 1.0,
																										"Children": [
																											{
																												"NodeType": "Link",
																												"LinkTarget": "MQ03_Event_Showdown"
																											}
																										]
																									},
																									{
																										"NodeType": "Choice",
																										"Title": "Randall",
																										"Tooltip": "Ask why Randall is chasing after her.",
																										"Highlight": false,
																										"ButtonWidth": 1.0,
																										"Children": [
																											{
																												"NodeType": "Link",
																												"LinkTarget": "MQ03_Event_Showdown"
																											}
																										]
																									},
																									{
																										"NodeType": "Choice",
																										"Title": "Plan",
																										"Tooltip": "Ask her what this 'plan' was that supposedly failed.",
																										"Highlight": false,
																										"ButtonWidth": 1.0,
																										"Children": [
																											{
																												"NodeType": "Link",
																												"LinkTarget": "MQ03_Event_Showdown"
																											}
																										]
																									},
																									{
																										"NodeType": "Choice",
																										"Title": "Panic",
																										"Tooltip": "Ask her why she is in such a panicked hurry.",
																										"Highlight": false,
																										"ButtonWidth": 1.0,
																										"Children": [
																											{
																												"NodeType": "Link",
																												"LinkTarget": "MQ03_Event_Showdown"
																											}
																										]
																									},
																									{
																										"NodeType": "Choice",
																										"Title": "Ring",
																										"Tooltip": "Ask her why you, not Iso, possess the ring.",
																										"Highlight": false,
																										"ButtonWidth": 1.0,
																										"Children": [
																											{
																												"NodeType": "Link",
																												"LinkTarget": "MQ03_Event_Showdown"
																											}
																										]
																									}
																								]
																							}
																						]
																					}
																				]
																			}
																		]
																	},
																	{
																		"NodeType": "Choice",
																		"Title": "How",
																		"Tooltip": "Ask her how she knows about this ring.",
																		"Highlight": false,
																		"ButtonWidth": 1.0,
																		"Children": [
																			{
																				"NodeType": "Link",
																				"LinkTarget": "MQ03_R_Intro5"
																			}
																		]
																	}
																]
															},
															{
																"NodeType": "State",
																"Key": "MQ03_R_Intro4Inv",
																"ScriptAction": {
																	"!Type": "ScriptDataVisualAction",
																	"Nodes": [
																		{
																			"!Type": "CommandLog",
																			"Text": "MQ03_TEMPLE_INTRO4",
																			"IsRaw": false
																		}
																	]
																},
																"Children": [
																	{
																		"NodeType": "Choice",
																		"Title": "Confirm",
																		"Tooltip": "Say that you do still have the strange ring you woke up with.",
																		"Highlight": false,
																		"ButtonWidth": 1.0,
																		"Children": [
																			{
																				"NodeType": "Link",
																				"LinkTarget": "MQ03_R_Intro5"
																			}
																		]
																	},
																	{
																		"NodeType": "Choice",
																		"Title": "How",
																		"Tooltip": "Ask her how she knows you woke up with a strange ring.",
																		"Highlight": false,
																		"ButtonWidth": 1.0,
																		"Children": [
																			{
																				"NodeType": "Link",
																				"LinkTarget": "MQ03_R_Intro5"
																			}
																		]
																	}
																]
															}
														]
													}
												]
											}
										]
									}
								]
							}
						]
					}
				]
			},
			{
				"NodeType": "State",
				"Key": "MQ03_Event_Showdown",
				"ScriptAction": {
					"!Type": "ScriptDataVisualAction",
					"Nodes": [
						{
							"!Type": "CommandSaveCheckpoint"
						},
						{
							"!Type": "CommandLog",
							"Text": "MQ03_TEMPLE_SHOWDOWN01",
							"IsRaw": false
						}
					]
				},
				"Children": [
					{
						"NodeType": "Choice",
						"Key": "MQ03_C_Showdown2",
						"Title": "Continue",
						"Highlight": false,
						"ButtonWidth": 1.0,
						"Children": [
							{
								"NodeType": "State",
								"Key": "MQ03_R_Showdown02",
								"ScriptAction": {
									"!Type": "ScriptDataVisualAction",
									"Nodes": [
										{
											"!Type": "CommandLog",
											"Text": "MQ03_TEMPLE_SHOWDOWN02",
											"IsRaw": false
										}
									]
								},
								"Children": [
									{
										"NodeType": "Choice",
										"Key": "MQ03_C_Showdown03",
										"Title": "Continue",
										"Highlight": false,
										"ButtonWidth": 1.0,
										"Children": [
											{
												"NodeType": "State",
												"Key": "MQ03_R_Showdown03",
												"ScriptAction": {
													"!Type": "ScriptDataVisualAction",
													"Nodes": [
														{
															"!Type": "CommandLog",
															"Text": "MQ03_TEMPLE_SHOWDOWN03",
															"IsRaw": false
														}
													]
												},
												"Children": [
													{
														"NodeType": "Choice",
														"Key": "MQ03_C_Showdown04",
														"Title": "Continue",
														"Highlight": false,
														"ButtonWidth": 1.0,
														"Children": [
															{
																"NodeType": "State",
																"Key": "MQ03_R_Showdown04",
																"ScriptAction": {
																	"!Type": "ScriptDataVisualAction",
																	"Nodes": [
																		{
																			"!Type": "CommandLog",
																			"Text": "MQ03_TEMPLE_SHOWDOWN04",
																			"IsRaw": false
																		}
																	]
																},
																"Children": [
																	{
																		"NodeType": "Choice",
																		"Key": "MQ03_C_Showdown05B",
																		"Title": "Punch",
																		"Tooltip": "[Strength & Agility] Give Randall a good whack while he's staggered.",
																		"Highlight": false,
																		"ButtonWidth": 1.0,
																		"Children": [
																			{
																				"NodeType": "State",
																				"Key": "MQ03_R_Showdown05B",
																				"ScriptAction": {
																					"!Type": "ScriptDataVisualAction",
																					"Nodes": [
																						{
																							"!Type": "CommandLog",
																							"Text": "MQ03_TEMPLE_SHOWDOWN05B",
																							"IsRaw": false
																						},
																						{
																							"!Type": "CommandLog",
																							"Text": "MQ03_TEMPLE_SHOWDOWN05Z",
																							"IsRaw": false
																						}
																					]
																				},
																				"Children": [
																					{
																						"NodeType": "Choice",
																						"Key": "MQ03_C_Showdown06",
																						"Title": "Continue",
																						"Highlight": false,
																						"ButtonWidth": 1.0,
																						"Children": [
																							{
																								"NodeType": "State",
																								"Key": "MQ03_R_Showdown06",
																								"ScriptAction": {
																									"!Type": "ScriptDataVisualAction",
																									"Nodes": [
																										{
																											"!Type": "CommandLog",
																											"Text": "MQ03_TEMPLE_SHOWDOWN06",
																											"IsRaw": false
																										}
																									]
																								},
																								"Children": [
																									{
																										"NodeType": "Choice",
																										"Key": "MQ03_C_Showdown07",
																										"Title": "Continue",
																										"Highlight": false,
																										"ButtonWidth": 1.0,
																										"Children": [
																											{
																												"NodeType": "State",
																												"Key": "MQ03_R_Showdown07",
																												"ScriptAction": {
																													"!Type": "ScriptDataVisualAction",
																													"Nodes": [
																														{
																															"!Type": "CommandLog",
																															"Text": "MQ03_TEMPLE_SHOWDOWN07",
																															"IsRaw": false
																														}
																													]
																												},
																												"Children": [
																													{
																														"NodeType": "Choice",
																														"Key": "MQ03_C_Showdown08",
																														"Title": "Continue",
																														"Highlight": false,
																														"ButtonWidth": 1.0,
																														"Children": [
																															{
																																"NodeType": "State",
																																"Key": "MQ03_R_Showdown08",
																																"ScriptAction": {
																																	"!Type": "ScriptDataVisualAction",
																																	"Nodes": [
																																		{
																																			"!Type": "CommandLog",
																																			"Text": "MQ03_TEMPLE_SHOWDOWN08",
																																			"IsRaw": false
																																		}
																																	]
																																},
																																"Children": [
																																	{
																																		"NodeType": "Choice",
																																		"Key": "MQ03_C_Showdown09",
																																		"Title": "Continue",
																																		"Highlight": false,
																																		"ButtonWidth": 1.0,
																																		"Children": [
																																			{
																																				"NodeType": "Link",
																																				"LinkTarget": "MQ03_R_Showdown09"
																																			}
																																		]
																																	}
																																]
																															}
																														]
																													}
																												]
																											}
																										]
																									}
																								]
																							}
																						]
																					}
																				]
																			}
																		]
																	},
																	{
																		"NodeType": "Choice",
																		"Key": "MQ03_C_Showdown05A",
																		"Title": "Grapple",
																		"Tooltip": "[Body & Wits] Try to restrain Randall to buy Iso some time.",
																		"Highlight": false,
																		"ButtonWidth": 1.0,
																		"Children": [
																			{
																				"NodeType": "State",
																				"Key": "MQ03_R_Showdown05A",
																				"ScriptAction": {
																					"!Type": "ScriptDataVisualAction",
																					"Nodes": [
																						{
																							"!Type": "CommandLog",
																							"Text": "MQ03_TEMPLE_SHOWDOWN05A",
																							"IsRaw": false
																						},
																						{
																							"!Type": "CommandLog",
																							"Text": "MQ03_TEMPLE_SHOWDOWN05Z",
																							"IsRaw": false
																						}
																					]
																				},
																				"Children": [
																					{
																						"NodeType": "Link",
																						"LinkTarget": "MQ03_C_Showdown06"
																					}
																				]
																			}
																		]
																	}
																]
															}
														]
													}
												]
											}
										]
									}
								]
							},
							{
								"NodeType": "State",
								"Key": "MQ03_R_Showdown09",
								"ScriptAction": {
									"!Type": "ScriptDataVisualAction",
									"Nodes": [
										{
											"!Type": "CommandSetLocation",
											"OperandMode": "Literal",
											"OperandText": "South Finmer, Docks"
										},
										{
											"!Type": "CommandLogSplit"
										},
										{
											"!Type": "CommandSaveCheckpoint"
										},
										{
											"!Type": "CommandInlineSnippet",
											"Snippet": "AdvanceTime(1)"
										},
										{
											"!Type": "CommandLog",
											"Text": "MQ03_TEMPLE_SHOWDOWN09",
											"IsRaw": false
										}
									]
								},
								"Children": [
									{
										"NodeType": "Choice",
										"Key": "MQ03_C_Showdown10",
										"Title": "Continue",
										"Highlight": false,
										"ButtonWidth": 1.0,
										"Children": [
											{
												"NodeType": "State",
												"Key": "MQ03_R_Showdown10",
												"ScriptAction": {
													"!Type": "ScriptDataVisualAction",
													"Nodes": [
														{
															"!Type": "CommandGrammarSetContext",
															"VariableName": "assailant",
															"CreatureGuid": "faeb4850-2ec9-483f-acc7-67ce5398d812"
														},
														{
															"!Type": "CommandCombatBegin",
															"IncludePlayer": true,
															"IncludeAllies": true,
															"Participants": [
																{
																	"Variable": "goon",
																	"Creature": "faeb4850-2ec9-483f-acc7-67ce5398d812",
																	"IsAlly": false
																}
															],
															"HasCallbackCombatStart": false,
															"HasCallbackRoundEnd": false,
															"HasCallbackPlayerKilled": false,
															"HasCallbackCreatureKilled": false,
															"HasCallbackCreatureVored": true,
															"CallbackCreatureVored": [
																{
																	"!Type": "CommandIf",
																	"Mode": "All",
																	"Operand": true,
																	"Tests": [
																		{
																			"!Type": "ConditionCombatParSwallowed",
																			"ParticipantName": "goon"
																		}
																	],
																	"HasElseBranch": false,
																	"MainSubgroup": [
																		{
																			"!Type": "CommandVarSetFlag",
																			"VariableName": "MQ03_TEMPLE_PRED_EATEN",
																			"OperandMode": "Literal",
																			"OperandLiteral": true
																		}
																	]
																}
															],
															"HasCallbackCreatureReleased": false
														},
														{
															"!Type": "CommandLog",
															"Text": "MQ03_TEMPLE_SHOWDOWN10",
															"IsRaw": false
														}
													]
												},
												"Children": [
													{
														"NodeType": "Choice",
														"Key": "MQ03_C_Showdown11",
														"Title": "Continue",
														"Highlight": false,
														"ButtonWidth": 1.0,
														"Children": [
															{
																"NodeType": "State",
																"Key": "MQ03_R_Showdown11A",
																"ScriptAction": {
																	"!Type": "ScriptDataVisualAction",
																	"Nodes": [
																		{
																			"!Type": "CommandLog",
																			"Text": "MQ03_TEMPLE_SHOWDOWN11A",
																			"IsRaw": false
																		}
																	]
																},
																"ScriptAppear": {
																	"!Type": "ScriptDataVisualCondition",
																	"Mode": "All",
																	"Operand": true,
																	"Tests": [
																		{
																			"!Type": "ConditionVarFlag",
																			"VariableName": "MQ03_TEMPLE_PRED_EATEN",
																			"OperandMode": "Literal",
																			"OperandLiteral": true
																		}
																	]
																},
																"Children": [
																	{
																		"NodeType": "Choice",
																		"Key": "MQ03_C_Showdown12",
																		"Title": "Continue",
																		"Highlight": false,
																		"ButtonWidth": 1.0,
																		"Children": [
																			{
																				"NodeType": "State",
																				"Key": "MQ03_R_Showdown12",
																				"ScriptAction": {
																					"!Type": "ScriptDataVisualAction",
																					"Nodes": [
																						{
																							"!Type": "CommandLog",
																							"Text": "MQ03_TEMPLE_SHOWDOWN12",
																							"IsRaw": false
																						}
																					]
																				},
																				"Children": [
																					{
																						"NodeType": "Choice",
																						"Key": "MQ03_C_Showdown13",
																						"Title": "Continue",
																						"Highlight": false,
																						"ButtonWidth": 1.0,
																						"ScriptAction": {
																							"!Type": "ScriptDataInline",
																							"Script": "AdvanceTime(1)"
																						},
																						"Children": [
																							{
																								"NodeType": "State",
																								"Key": "MQ03_R_Showdown13A",
																								"ScriptAction": {
																									"!Type": "ScriptDataVisualAction",
																									"Nodes": [
																										{
																											"!Type": "CommandLog",
																											"Text": "MQ03_TEMPLE_SHOWDOWN13A",
																											"IsRaw": false
																										}
																									]
																								},
																								"ScriptAppear": {
																									"!Type": "ScriptDataVisualCondition",
																									"Mode": "All",
																									"Operand": true,
																									"Tests": [
																										{
																											"!Type": "ConditionVarFlag",
																											"VariableName": "MQ03_TEMPLE_PRED_EATEN",
																											"OperandMode": "Literal",
																											"OperandLiteral": true
																										}
																									]
																								},
																								"Children": [
																									{
																										"NodeType": "Choice",
																										"Key": "MQ03_C_Showdown14",
																										"Title": "Continue",
																										"Highlight": false,
																										"ButtonWidth": 1.0,
																										"Children": [
																											{
																												"NodeType": "State",
																												"Key": "MQ03_R_Showdown14",
																												"ScriptAction": {
																													"!Type": "ScriptDataVisualAction",
																													"Nodes": [
																														{
																															"!Type": "CommandLog",
																															"Text": "MQ03_TEMPLE_SHOWDOWN14",
																															"IsRaw": false
																														}
																													]
																												},
																												"Children": [
																													{
																														"NodeType": "Choice",
																														"Key": "MQ03_C_Finish",
																														"Title": "Continue",
																														"Highlight": false,
																														"ButtonWidth": 1.0,
																														"ScriptAction": {
																															"!Type": "ScriptDataVisualAction",
																															"Nodes": [
																																{
																																	"!Type": "CommandComment",
																																	"Comment": "Complete MQ03"
																																},
																																{
																																	"!Type": "CommandVarSetFlag",
																																	"VariableName": "MQ03_DONE",
																																	"OperandMode": "Literal",
																																	"OperandLiteral": true
																																},
																																{
																																	"!Type": "CommandVarSetNumber",
																																	"VariableName": "MQ03_PORT_LOCK",
																																	"ValueOperation": "Set",
																																	"OperandMode": "Script",
																																	"OperandText": "GetTimeHourTotal()"
																																},
																																{
																																	"!Type": "CommandPlayerAddXP",
																																	"OperandMode": "Script",
																																	"OperandText": "RewardXP.MQ03_Complete"
																																},
																																{
																																	"!Type": "CommandJournalClose",
																																	"JournalGuid": "fb14b2b1-f0cf-474d-a311-720266f557d3"
																																},
																																{
																																	"!Type": "CommandJournalUpdate",
																																	"JournalGuid": "91d32e80-0d61-45d3-8d5f-a6f810689849",
																																	"Stage": 10
																																},
																																{
																																	"!Type": "CommandComment",
																																	"Comment": "Return player to town"
																																},
																																{
																																	"!Type": "CommandSetScene",
																																	"SceneGuid": "f27d5789-2f77-49dd-bd74-1b7d220e7ea1"
																																}
																															]
																														},
																														"Children": []
																													}
																												]
																											}
																										]
																									}
																								]
																							},
																							{
																								"NodeType": "State",
																								"Key": "MQ03_R_Showdown13B",
																								"ScriptAction": {
																									"!Type": "ScriptDataVisualAction",
																									"Nodes": [
																										{
																											"!Type": "CommandLog",
																											"Text": "MQ03_TEMPLE_SHOWDOWN13B",
																											"IsRaw": false
																										}
																									]
																								},
																								"Children": [
																									{
																										"NodeType": "Link",
																										"LinkTarget": "MQ03_C_Showdown14"
																									}
																								]
																							}
																						]
																					}
																				]
																			}
																		]
																	}
																]
															},
															{
																"NodeType": "State",
																"Key": "MQ03_R_Showdown11B",
																"ScriptAction": {
																	"!Type": "ScriptDataVisualAction",
																	"Nodes": [
																		{
																			"!Type": "CommandLog",
																			"Text": "MQ03_TEMPLE_SHOWDOWN11B",
																			"IsRaw": false
																		}
																	]
																},
																"Children": [
																	{
																		"NodeType": "Link",
																		"LinkTarget": "MQ03_C_Showdown12"
																	}
																]
															}
														]
													}
												]
											}
										]
									}
								]
							}
						]
					}
				]
			}
		]
	}
}